gym_toytext/__init__.py
gym_toytext/guessing_game.py
gym_toytext/hotter_colder.py
gym_toytext/kellycoinflip.py
gym_toytext/nchain.py
gym_toytext/roulette.py
gym_legacy_toytext-0.0.5.dist-info/METADATA
gym_legacy_toytext-0.0.5.dist-info/WHEEL
gym_legacy_toytext-0.0.5.dist-info/top_level.txt
gym_legacy_toytext-0.0.5.dist-info/RECORD
