Metadata-Version: 2.1
Name: gym-legacy-toytext
Version: 0.0.5
Summary: Legacy Toytext Environments from OpenAI Gym
Home-page: https://github.com/Rohan138/gym-legacy-toytext
Author: Rohan Potdar
Author-email: rohanpotdar138@gmail.com
Classifier: Programming Language :: Python :: 3
Classifier: Programming Language :: Python :: 3.6
Classifier: Programming Language :: Python :: 3.7
Classifier: Programming Language :: Python :: 3.8
Classifier: Programming Language :: Python :: 3.9
Classifier: Programming Language :: Python :: 3.10
Requires-Python: >=3.6
Requires-Dist: gym (<0.26.0,>=0.19.0)
